eyesopen/__init__.py
eyesopen/image_analysis.py
eyesopen/main.py
eyesopen/utilities.py
eyesopen-0.1.5.dist-info/LICENSE
eyesopen-0.1.5.dist-info/METADATA
eyesopen-0.1.5.dist-info/WHEEL
eyesopen-0.1.5.dist-info/entry_points.txt
eyesopen-0.1.5.dist-info/top_level.txt
eyesopen-0.1.5.dist-info/RECORD
