Metadata-Version: 2.1
Name: eyesopen
Version: 0.1.5
Summary: A simple digital forensics tool.
License: # GNU GENERAL PUBLIC LICENSE
Classifier: Development Status :: 5 - Production/Stable
Classifier: Intended Audience :: Developers
Classifier: License :: OSI Approved :: GNU General Public License v3 or later (GPLv3+)
Classifier: Programming Language :: Python :: 3
Classifier: Programming Language :: Python :: 3.11
License-File: LICENSE
Requires-Dist: imageio ==2.31.5
Requires-Dist: lazy-loader ==0.3
Requires-Dist: networkx ==3.1
Requires-Dist: numpy ==1.26.0
Requires-Dist: opencv-python ==4.8.1.78
Requires-Dist: packaging ==23.2
Requires-Dist: Pillow ==10.0.1
Requires-Dist: PyWavelets ==1.4.1
Requires-Dist: scikit-image ==0.22.0
Requires-Dist: scipy ==1.11.3
Requires-Dist: termcolor ==2.3.0
Requires-Dist: tifffile ==2023.9.26
Requires-Dist: click ==8.1.7
